bdba/__init__.py
bdba/client.py
bdba/model.py
bdba/util.py
bdba-0.9.0.dist-info/LICENSE
bdba-0.9.0.dist-info/METADATA
bdba-0.9.0.dist-info/WHEEL
bdba-0.9.0.dist-info/top_level.txt
bdba-0.9.0.dist-info/RECORD
