Metadata-Version: 2.1
Name: bdba
Version: 0.9.0
Requires-Python: >=3.11
License-File: LICENSE
Requires-Dist: cachecontrol
Requires-Dist: dacite
Requires-Dist: python-dateutil
Requires-Dist: requests
